abris_transform
