Metadata-Version: 1.1
Name: abris
Version: 0.1.4
Summary: Small data preprocessing engine built on top of sklearn for easy prototyping.
Home-page: https://github.com/Skabed/abris
Author: Gerard Madorell
Author-email: gmadorell@gmail.com
License: UNKNOWN
Download-URL: https://github.com/Skabed/abris/tarball/0.1.3
Keywords: preprocessing,data
Platform: UNKNOWN
